alarmeVeicular.vhd
LIBRARY ieee;
USE ieee.std_logic_1164.ALL;

ENTITY alarmeVeicular IS
	PORT(
		k1_porta : IN STD_LOGIC;
		k2_ing : IN STD_LOGIC;
		k3_farol : IN STD_LOGIC;
		buzzer : OUT STD_LOGIC
	);
END alarmeVeicular;

ARCHITECTURE behavior of alarmeVeicular IS
	SIGNAL alarme : STD_LOGIC;
BEGIN
	PROCESS(k1_porta, k2_ing, k3_farol)
	BEGIN 
		buzzer <= '1';
		
		if (k2_ing <= '0') then
			if (k1_porta <= '0') then
				buzzer <= '0';
			end if;
		elsif (k2_ing <= '1') then
			if (k3_farol <= '0') then
				buzzer <= '0';
			end if;
		end if;
	end PROCESS;
end behavior;

tb_alarmeVeicular.vhd
LIBRARY ieee;
USE ieee.std_logic_1164.ALL;

ENTITY tb_alarmeVeicular IS
END tb_alarmeVeicular;

ARCHITECTURE behavior OF tb_alarmeVeicular IS
	COMPONENT alarmeVeicular
		PORT(
			k1_porta : IN STD_LOGIC;
			k2_ing : IN STD_LOGIC;
			k3_farol : IN STD_LOGIC;
			buzzer : OUT STD_LOGIC
		);
	END COMPONENT;

	SIGNAL k1_porta : STD_LOGIC := '0';
	SIGNAL k2_ing : STD_LOGIC := '0';
	SIGNAL k3_farol : STD_LOGIC := '0';
	SIGNAL buzzer : STD_LOGIC;
	
BEGIN 
	uut: alarmeVeicular PORT MAP(
		k1_porta => k1_porta,
		k2_ing => k2_ing,
		k3_farol => k3_farol,
		buzzer => buzzer
	);
	
	stim_proc: PROCESS
	BEGIN
		k1_porta <= '0'; k2_ing <= '0'; k3_farol <= '0'; --000
      WAIT FOR 10 ns;

      k1_porta <= '0'; k2_ing <= '0'; k3_farol <= '1'; --001 
      WAIT FOR 10 ns;

      k1_porta <= '0'; k2_ing <= '1'; k3_farol <= '0'; --010
      WAIT FOR 10 ns;

      k1_porta <= '0'; k2_ing <= '1'; k3_farol <= '1'; --011 
      WAIT FOR 10 ns;

      k1_porta <= '1'; k2_ing <= '0'; k3_farol <= '0'; --100 
      WAIT FOR 10 ns;

      k1_porta <= '1'; k2_ing <= '0'; k3_farol <= '1'; --101
      WAIT FOR 10 ns;

      k1_porta <= '1'; k2_ing <= '1'; k3_farol <= '0'; --110 
		WAIT FOR 10 ns;

      k1_porta <= '1'; k2_ing <= '1'; k3_farol <= '1'; --111
		WAIT FOR 10 ns;
		
		WAIT;
	END PROCESS;
END behavior;

projeto_alarmeVeiculo/onda.vcd
$date
  Wed Jan 29 11:25:46 2025
$end
$version
  GHDL v0
$end
$timescale
  1 fs
$end
$scope module standard $end
$upscope $end
$scope module std_logic_1164 $end
$upscope $end
$scope module tb_alarmeveicular $end
$var reg 1 ! k1_porta $end
$var reg 1 " k2_ing $end
$var reg 1 # k3_farol $end
$var reg 1 $ buzzer $end
$scope module uut $end
$var reg 1 % k1_porta $end
$var reg 1 & k2_ing $end
$var reg 1 ' k3_farol $end
$var reg 1 ( buzzer $end
$var reg 1 ) alarme $end
$upscope $end
$upscope $end
$enddefinitions $end
#0
0!
0"
0#
0$
0%
0&
0'
0(
U)
#10000000
1#
1'
0(
#20000000
1"
0#
1&
0'
0(
#30000000
1#
1$
1'
1(
#40000000
1!
0"
0#
1%
0&
0'
#50000000
1#
1'
#60000000
1"
0#
0$
1&
0'
0(
#70000000
1#
1$
1'
1(
