projeto_detectorParidade/detectorParidade.vhd
LIBRARY ieee;
USE ieee.std_logic_1164.ALL;

ENTITY detectorParidade IS
	PORT (
		key1 : IN STD_LOGIC;
		key2 : IN STD_LOGIC;
		key3 : IN STD_LOGIC;
		led0 : OUT STD_LOGIC;
		led1 : OUT STD_LOGIC
	);
END detectorParidade;

ARCHITECTURE behavior OF detectorParidade IS 
	SIGNAL paridade : STD_LOGIC;
BEGIN
	PROCESS (key1, key2, key3)
	BEGIN 
			paridade <= key1 XOR key2 XOR key3;
			led0 <= NOT paridade;
			led1 <= paridade;
	END PROCESS;
END behavior;

projeto_detectorParidade/tb_detectorParidade.vhd
LIBRARY ieee;
USE ieee.std_logic_1164.ALL;

ENTITY tb_detectorParidade IS 
END tb_detectorParidade;

ARCHITECTURE behavior OF tb_detectorParidade IS

	COMPONENT detectorParidade
		PORT(
			key1 : IN STD_LOGIC;
			key2 : IN STD_LOGIC;
			key3 : IN STD_LOGIC;
			led0 : OUT STD_LOGIC;
			led1 : OUT STD_LOGIC
		);
	END COMPONENT;
	
	SIGNAL key1 : STD_LOGIC := '0';
	SIGNAL key2 : STD_LOGIC := '0';
	SIGNAL key3 : STD_LOGIC := '0';
	SIGNAL led0 : STD_LOGIC;
	SIGNAL led1 : STD_LOGIC;
	
BEGIN 
	uut: detectorParidade PORT MAP(
		key1 => key1,
		key2 => key2,
		key3 => key3,
		led0 => led0,
		led1 => led1
	);
	
	stim_proc: PROCESS
	BEGIN
		key1 <= '0'; key2 <= '0'; key3 <= '0';
		WAIT FOR 10 ns;
		
		key1 <= '0'; key2 <= '0'; key3 <= '1';
		WAIT FOR 10 ns;
		
		key1 <= '0'; key2 <= '1'; key3 <= '0';
		WAIT FOR 10 ns;
		
		key1 <= '0'; key2 <= '1'; key3 <= '1';
		WAIT FOR 10 ns;
		
		key1 <= '1'; key2 <= '0'; key3 <= '0';
		WAIT FOR 10 ns;
		
		key1 <= '1'; key2 <= '0'; key3 <= '1';
		WAIT FOR 10 ns;
		
		key1 <= '1'; key2 <= '1'; key3 <= '0';
		WAIT FOR 10 ns;
		
		key1 <= '1'; key2 <= '1'; key3 <= '1';
		WAIT FOR 10 ns;
		
		WAIT;
	END PROCESS;
END behavior;

projeto_detectorParidade/onda.vcd
$date
  Mon Jan 20 17:41:33 2025
$end
$version
  GHDL v0
$end
$timescale
  1 fs
$end
$scope module standard $end
$upscope $end
$scope module std_logic_1164 $end
$upscope $end
$scope module tb_detectorparidade $end
$var reg 1 ! key1 $end
$var reg 1 " key2 $end
$var reg 1 # key3 $end
$var reg 1 $ led0 $end
$var reg 1 % led1 $end
$scope module uut $end
$var reg 1 & key1 $end
$var reg 1 ' key2 $end
$var reg 1 ( key3 $end
$var reg 1 ) led0 $end
$var reg 1 * led1 $end
$var reg 1 + paridade $end
$upscope $end
$upscope $end
$enddefinitions $end
#0
0!
0"
0#
U$
U%
0&
0'
0(
U)
U*
0+
#10000000
1#
1$
0%
1(
1)
0*
1+
#20000000
1"
0#
0$
1%
1'
0(
0)
1*
#30000000
1#
1(
0+
#40000000
1!
0"
0#
1$
0%
1&
0'
0(
1)
0*
1+
#50000000
1#
0$
1%
1(
0)
1*
0+
#60000000
1"
0#
1$
0%
1'
0(
1)
0*
#70000000
1#
1(
1+
